covacha_IA/__init__.py
covacha_IA/config.py
covacha_IA/open_ia.py
covacha_IA/openia_assistant.py
covacha_IA/openia_base.py
covacha_IA/openia_thread.py
test/__init__.py
test/test_config.py
test/test_openia_base.py
covachaIA-0.1.dist-info/LICENSE
covachaIA-0.1.dist-info/METADATA
covachaIA-0.1.dist-info/WHEEL
covachaIA-0.1.dist-info/top_level.txt
covachaIA-0.1.dist-info/RECORD
